Assembly_VerilogAndLogicGates/TTL/sn7474/behaviour.v
//================================================================--
// Design Unit	: sn7474 (behaviour) 
//
// File Name	: behaviour.v
//
// Purpose	: model of TTL SN7474 dual edge-triggered D FF IC
//
// Author	: Peter Walsh, Vancouver Island University
//
// Environmant	: Icarus
//-------------------------------------------------------------------
// Revision List	
// Version	Author	Date	Changes
// 1.0		PW	Sept 10 New version
//================================================================--

module sn7474 (P1, P2, P3, P4, P5, P6, P7, P8, P9, P10, P11, P12, P13, P14); 

   output reg P5, P6, P8, P9;
   input P1, P2, P3, P4, P7, P10, P11, P12, P13, P14;

   always @ (posedge P3) begin
      if ((P14 == 1) && (P7 == 0) && (P1 == 1) && (P4 == 1)) begin
         P5 <= P2;
         P6 <= ~P2;
      end
   end

   always @ (P1, P4, P7, P14) begin
      if ((P14 == 1) && (P7 == 0)) begin
         if ((P1 == 0) && (P4 == 1)) begin
            P5 <= 1'b 0;
            P6 <= 1'b 1;
         end
         if ((P4 == 0) && (P1 == 1)) begin
            P5 <= 1'b 1;
            P6 <= 1'b 0;
         end
      end
   end

   always @ (posedge P11) begin
      if ((P14 == 1) && (P7 == 0)) begin
         P9 <= P12;
         P8 <= ~P12;
      end
   end

   always @ (P10, P13, P7, P14) begin
      if ((P14 == 1) && (P7 == 0)) begin
         if ((P13 == 0) && (P10 == 1)) begin
            P9 <= 1'b 0;
            P8 <= 1'b 1;
         end
         if ((P10 == 0) && (P13 == 1)) begin
            P9 <= 1'b 1;
            P8 <= 1'b 0;
         end
      end
   end

endmodule

Assembly_VerilogAndLogicGates/TTL/sn7474/tb.v
//================================================================--
// Design Unit  : cew testbench for sn7474
//
// File Name    : tb.cew
//
// Purpose      : design verification
//
// Author       : Peter Walsh, Vancouver Island University
//
// System       : icarus (Linux)
//
//------------------------------------------------------------------
// Revision List
// Version      Author  Date    Changes
// 1.0          PW      Sep 10  New version
//================================================================--











module test_bench();

   integer cew_Test_Count=0;
          integer cew_Error_Count=0;

   wire t_P5, t_P6, t_P8, t_P9;
   reg t_P1, t_P2, t_P3, t_P4, t_P7, t_P10, t_P11, t_P12, t_P13, t_P14;

   sn7474 cut(t_P1, t_P2, t_P3, t_P4, t_P5, t_P6, t_P7, t_P8, t_P9, t_P10, t_P11, t_P12, t_P13, t_P14);

   task clockTick1; // nasty syntax but task body can only be one (compound) statement
      begin
         t_P3=0; #3;
         t_P3=1; #6;
         t_P3=0; #3;
      end
   endtask

   task clockTick2;
      begin
         t_P11=0; #3;
         t_P11=1; #6;
         t_P11=0; #3;
      end
   endtask


   initial begin
      $dumpfile("test_bench.vcd");
      $dumpvars(0,test_bench);

      t_P14=1; t_P7=0; 
      
      // Async Operation

      cew_Test_Count=cew_Test_Count+1;
          t_P1=1; t_P4=0; #1; t_P4=1; #1;
          if ((t_P5) !== (1)) begin
             cew_Error_Count=cew_Error_Count+1;
             $display("\nTest Case ERROR (Ncase) in script at line number 53");
             $display("Actual Value is ", t_P5 );
             $display("Expected Value is ", 1 );
          end

      cew_Test_Count=cew_Test_Count+1;
          
          if ((t_P6) !== (0)) begin
             cew_Error_Count=cew_Error_Count+1;
             $display("\nTest Case ERROR (Ncase) in script at line number 54");
             $display("Actual Value is ", t_P6 );
             $display("Expected Value is ", 0 );
          end


      cew_Test_Count=cew_Test_Count+1;
          t_P1=0; t_P4=1; #1; t_P1=1; #1;
          if ((t_P5) !== (0)) begin
             cew_Error_Count=cew_Error_Count+1;
             $display("\nTest Case ERROR (Ncase) in script at line number 56");
             $display("Actual Value is ", t_P5 );
             $display("Expected Value is ", 0 );
          end

      cew_Test_Count=cew_Test_Count+1;
          
          if ((t_P6) !== (1)) begin
             cew_Error_Count=cew_Error_Count+1;
             $display("\nTest Case ERROR (Ncase) in script at line number 57");
             $display("Actual Value is ", t_P6 );
             $display("Expected Value is ", 1 );
          end


      cew_Test_Count=cew_Test_Count+1;
          t_P13=1; t_P10=0; #1; t_P10=1; #1;
          if ((t_P9) !== (1)) begin
             cew_Error_Count=cew_Error_Count+1;
             $display("\nTest Case ERROR (Ncase) in script at line number 59");
             $display("Actual Value is ", t_P9 );
             $display("Expected Value is ", 1 );
          end

      cew_Test_Count=cew_Test_Count+1;
          
          if ((t_P8) !== (0)) begin
             cew_Error_Count=cew_Error_Count+1;
             $display("\nTest Case ERROR (Ncase) in script at line number 60");
             $display("Actual Value is ", t_P8 );
             $display("Expected Value is ", 0 );
          end


      cew_Test_Count=cew_Test_Count+1;
          t_P13=0; t_P10=1; #1; t_P13=1; #1;
          if ((t_P9) !== (0)) begin
             cew_Error_Count=cew_Error_Count+1;
             $display("\nTest Case ERROR (Ncase) in script at line number 62");
             $display("Actual Value is ", t_P9 );
             $display("Expected Value is ", 0 );
          end

      cew_Test_Count=cew_Test_Count+1;
          
          if ((t_P8) !== (1)) begin
             cew_Error_Count=cew_Error_Count+1;
             $display("\nTest Case ERROR (Ncase) in script at line number 63");
             $display("Actual Value is ", t_P8 );
             $display("Expected Value is ", 1 );
          end



      // Normal Operation
      
      t_P1=1; t_P4=1; t_P10=1; t_P13=1; 

      cew_Test_Count=cew_Test_Count+1;
          t_P2=1;clockTick1();
          if ((t_P5) !== (1)) begin
             cew_Error_Count=cew_Error_Count+1;
             $display("\nTest Case ERROR (Ncase) in script at line number 70");
             $display("Actual Value is ", t_P5 );
             $display("Expected Value is ", 1 );
          end

      cew_Test_Count=cew_Test_Count+1;
          
          if ((t_P6) !== (0)) begin
             cew_Error_Count=cew_Error_Count+1;
             $display("\nTest Case ERROR (Ncase) in script at line number 71");
             $display("Actual Value is ", t_P6 );
             $display("Expected Value is ", 0 );
          end


      cew_Test_Count=cew_Test_Count+1;
          t_P12=1;clockTick2();
          if ((t_P9) !== (1)) begin
             cew_Error_Count=cew_Error_Count+1;
             $display("\nTest Case ERROR (Ncase) in script at line number 73");
             $display("Actual Value is ", t_P9 );
             $display("Expected Value is ", 1 );
          end

      cew_Test_Count=cew_Test_Count+1;
          
          if ((t_P8) !== (0)) begin
             cew_Error_Count=cew_Error_Count+1;
             $display("\nTest Case ERROR (Ncase) in script at line number 74");
             $display("Actual Value is ", t_P8 );
             $display("Expected Value is ", 0 );
          end


      cew_Test_Count=cew_Test_Count+1;
          t_P2=0;clockTick1();
          if ((t_P5) !== (0)) begin
             cew_Error_Count=cew_Error_Count+1;
             $display("\nTest Case ERROR (Ncase) in script at line number 76");
             $display("Actual Value is ", t_P5 );
             $display("Expected Value is ", 0 );
          end

      cew_Test_Count=cew_Test_Count+1;
          
          if ((t_P6) !== (1)) begin
             cew_Error_Count=cew_Error_Count+1;
             $display("\nTest Case ERROR (Ncase) in script at line number 77");
             $display("Actual Value is ", t_P6 );
             $display("Expected Value is ", 1 );
          end


      cew_Test_Count=cew_Test_Count+1;
          t_P12=0;clockTick2();
          if ((t_P9) !== (0)) begin
             cew_Error_Count=cew_Error_Count+1;
             $display("\nTest Case ERROR (Ncase) in script at line number 79");
             $display("Actual Value is ", t_P9 );
             $display("Expected Value is ", 0 );
          end

      cew_Test_Count=cew_Test_Count+1;
          
          if ((t_P8) !== (1)) begin
             cew_Error_Count=cew_Error_Count+1;
             $display("\nTest Case ERROR (Ncase) in script at line number 80");
             $display("Actual Value is ", t_P8 );
             $display("Expected Value is ", 1 );
          end




      $display("\n**********Summary**********\n");
          $display("Total number of test cases = %d \n", cew_Test_Count);
          $display("Total number of test cases in error = %d \n", cew_Error_Count);

      #1 $finish();
   end

endmodule

Assembly_VerilogAndLogicGates/TTL/sn7474/test_bench.vcd
$date
	Thu Nov 21 15:50:31 2013
$end
$version
	Icarus Verilog
$end
$timescale
	1s
$end
$scope module test_bench $end
$var wire 1 ! t_P5 $end
$var wire 1 " t_P6 $end
$var wire 1 # t_P8 $end
$var wire 1 $ t_P9 $end
$var integer 32 % cew_Error_Count [31:0] $end
$var integer 32 & cew_Test_Count [31:0] $end
$var reg 1 ' t_P1 $end
$var reg 1 ( t_P10 $end
$var reg 1 ) t_P11 $end
$var reg 1 * t_P12 $end
$var reg 1 + t_P13 $end
$var reg 1 , t_P14 $end
$var reg 1 - t_P2 $end
$var reg 1 . t_P3 $end
$var reg 1 / t_P4 $end
$var reg 1 0 t_P7 $end
$scope module cut $end
$var wire 1 1 P1 $end
$var wire 1 2 P10 $end
$var wire 1 3 P11 $end
$var wire 1 4 P12 $end
$var wire 1 5 P13 $end
$var wire 1 6 P14 $end
$var wire 1 7 P2 $end
$var wire 1 8 P3 $end
$var wire 1 9 P4 $end
$var wire 1 : P7 $end
$var reg 1 ; P5 $end
$var reg 1 < P6 $end
$var reg 1 = P8 $end
$var reg 1 > P9 $end
$upscope $end
$scope task clockTick1 $end
$upscope $end
$scope task clockTick2 $end
$upscope $end
$upscope $end
$enddefinitions $end
#0
$dumpvars
x>
x=
0<
1;
0:
09
x8
x7
16
x5
x4
x3
x2
11
00
0/
x.
x-
1,
x+
x*
x)
x(
1'
b1 &
b0 %
x$
x#
0"
1!
$end
#1
1/
19
#2
1<
1"
0;
0!
0'
01
b11 &
#3
1'
11
#4
0=
0#
1>
1$
0(
02
1+
15
b101 &
#5
1(
12
#6
1=
1#
0>
0$
0+
05
b111 &
#7
1+
15
#8
0.
08
1-
17
b1001 &
#11
0<
0"
1;
1!
1.
18
#17
0.
08
#20
0)
03
1*
14
b1011 &
#23
0=
0#
1>
1$
1)
13
#29
0)
03
#32
0-
07
b1101 &
#35
1<
1"
0;
0!
1.
18
#41
0.
08
#44
0*
04
b1111 &
#47
1=
1#
0>
0$
1)
13
#53
0)
03
#56
b10000 &
