Assembly_VerilogAndLogicGates/TTL/sn7404/behaviour.v
//================================================================--
// Design Unit	: sn7404 (behaviour)
//
// File Name	: behaviour.v
//
// Purpose	: model of TTL SN7404 hex inverter IC
//
// Author	: Peter Walsh, Vancouver Island University
//
// Environmant	: Icarus
//-------------------------------------------------------------------
// Revision List	
// Version	Author	Date	Changes
// 1.0		PW	Sept 10 New version
//================================================================--

module sn7404 (P1, P2, P3, P4, P5, P6, P7, P8, P9, P10, P11, P12, P13, P14); 

   output P2, P4, P6, P8, P10, P12;
   input P1, P3, P5, P7, P9, P11, P13, P14;

   reg P2, P4, P6, P8, P10, P12;

   always @(P1, P7, P14) begin

      if ((P14 == 1'b 1) && (P7 == 1'b 0)) begin
         P2 = ~P1;
      end
   end

   always @(P3, P7, P14) begin

      if ((P14 == 1'b 1) && (P7 == 1'b 0)) begin
         P4 = ~P3;
      end
   end

   always @(P5, P7, P14) begin

      if ((P14 == 1'b 1) && (P7 == 1'b 0)) begin
         P6 = ~P5;
      end
   end

   always @(P7, P9, P14) begin

      if ((P14 == 1'b 1) && (P7 == 1'b 0)) begin
         P8 = ~P9;
      end
   end

   always @(P7, P11, P14) begin

      if ((P14 == 1'b 1) && (P7 == 1'b 0)) begin
         P10 = ~P11;
      end
   end

   always @(P7, P13, P14) begin

      if ((P14 == 1'b 1) && (P7 == 1'b 0)) begin
         P12 = ~P13;
      end
   end

endmodule

Assembly_VerilogAndLogicGates/TTL/sn7404/tb.v
//================================================================--
// Design Unit  : cew testbench for sn7404
//
// File Name    : tb.cew
//
// Purpose      : design verification
//
// Note         :
//
// Limitations  :
//
// Errors       : none known
//
// Library      : sn7404 
//
// Dependences  : none
//
// Author       : Peter Walsh, Vancouver Island University
//
// System       : icarus (Linux)
//
//------------------------------------------------------------------
// Revision List
// Version      Author  Date    Changes
// 1.0          PW      Sep 10  New version
//================================================================--












module test_bench();

   integer cew_Test_Count=0;
          integer cew_Error_Count=0;

   wire t_P2, t_P4, t_P6, t_P8, t_P10, t_P12;
   reg t_P1, t_P3, t_P5, t_P7, t_P9, t_P11, t_P13, t_P14;

   sn7404 cut(t_P1, t_P2, t_P3, t_P4, t_P5, t_P6, t_P7, t_P8, t_P9, t_P10, t_P11, t_P12, t_P13, t_P14);

   initial begin
      $dumpfile("test_bench.vcd");
      $dumpvars(0,test_bench);

      t_P14=1; t_P7=0;

      // note, gates are tested sequentially

      cew_Test_Count=cew_Test_Count+1;
          t_P1=0;#1;
          if ((t_P2) !== (1)) begin
             cew_Error_Count=cew_Error_Count+1;
             $display("\nTest Case ERROR (Ncase) in script at line number 47");
             $display("Actual Value is ", t_P2 );
             $display("Expected Value is ", 1 );
          end

      cew_Test_Count=cew_Test_Count+1;
          t_P1=1;#1;
          if ((t_P2) !== (0)) begin
             cew_Error_Count=cew_Error_Count+1;
             $display("\nTest Case ERROR (Ncase) in script at line number 48");
             $display("Actual Value is ", t_P2 );
             $display("Expected Value is ", 0 );
          end


      cew_Test_Count=cew_Test_Count+1;
          t_P3=0;#1;
          if ((t_P4) !== (1)) begin
             cew_Error_Count=cew_Error_Count+1;
             $display("\nTest Case ERROR (Ncase) in script at line number 50");
             $display("Actual Value is ", t_P4 );
             $display("Expected Value is ", 1 );
          end

      cew_Test_Count=cew_Test_Count+1;
          t_P3=1;#1;
          if ((t_P4) !== (0)) begin
             cew_Error_Count=cew_Error_Count+1;
             $display("\nTest Case ERROR (Ncase) in script at line number 51");
             $display("Actual Value is ", t_P4 );
             $display("Expected Value is ", 0 );
          end


      cew_Test_Count=cew_Test_Count+1;
          t_P5=0;#1;
          if ((t_P6) !== (1)) begin
             cew_Error_Count=cew_Error_Count+1;
             $display("\nTest Case ERROR (Ncase) in script at line number 53");
             $display("Actual Value is ", t_P6 );
             $display("Expected Value is ", 1 );
          end

      cew_Test_Count=cew_Test_Count+1;
          t_P5=1;#1;
          if ((t_P6) !== (0)) begin
             cew_Error_Count=cew_Error_Count+1;
             $display("\nTest Case ERROR (Ncase) in script at line number 54");
             $display("Actual Value is ", t_P6 );
             $display("Expected Value is ", 0 );
          end


      cew_Test_Count=cew_Test_Count+1;
          t_P9=0;#1;
          if ((t_P8) !== (1)) begin
             cew_Error_Count=cew_Error_Count+1;
             $display("\nTest Case ERROR (Ncase) in script at line number 56");
             $display("Actual Value is ", t_P8 );
             $display("Expected Value is ", 1 );
          end

      cew_Test_Count=cew_Test_Count+1;
          t_P9=1;#1;
          if ((t_P8) !== (0)) begin
             cew_Error_Count=cew_Error_Count+1;
             $display("\nTest Case ERROR (Ncase) in script at line number 57");
             $display("Actual Value is ", t_P8 );
             $display("Expected Value is ", 0 );
          end


      cew_Test_Count=cew_Test_Count+1;
          t_P11=0;#1;
          if ((t_P10) !== (1)) begin
             cew_Error_Count=cew_Error_Count+1;
             $display("\nTest Case ERROR (Ncase) in script at line number 59");
             $display("Actual Value is ", t_P10 );
             $display("Expected Value is ", 1 );
          end

      cew_Test_Count=cew_Test_Count+1;
          t_P11=1;#1;
          if ((t_P10) !== (0)) begin
             cew_Error_Count=cew_Error_Count+1;
             $display("\nTest Case ERROR (Ncase) in script at line number 60");
             $display("Actual Value is ", t_P10 );
             $display("Expected Value is ", 0 );
          end


      cew_Test_Count=cew_Test_Count+1;
          t_P13=0;#1;
          if ((t_P12) !== (1)) begin
             cew_Error_Count=cew_Error_Count+1;
             $display("\nTest Case ERROR (Ncase) in script at line number 62");
             $display("Actual Value is ", t_P12 );
             $display("Expected Value is ", 1 );
          end

      cew_Test_Count=cew_Test_Count+1;
          t_P13=1;#1;
          if ((t_P12) !== (0)) begin
             cew_Error_Count=cew_Error_Count+1;
             $display("\nTest Case ERROR (Ncase) in script at line number 63");
             $display("Actual Value is ", t_P12 );
             $display("Expected Value is ", 0 );
          end


      $display("\n**********Summary**********\n");
          $display("Total number of test cases = %d \n", cew_Test_Count);
          $display("Total number of test cases in error = %d \n", cew_Error_Count);

      #1 $finish();
   end

endmodule

Assembly_VerilogAndLogicGates/TTL/sn7404/test_bench.vcd
$date
	Wed Oct 30 17:04:04 2013
$end
$version
	Icarus Verilog
$end
$timescale
	1s
$end
$scope module test_bench $end
$var wire 1 ! t_P10 $end
$var wire 1 " t_P12 $end
$var wire 1 # t_P2 $end
$var wire 1 $ t_P4 $end
$var wire 1 % t_P6 $end
$var wire 1 & t_P8 $end
$var integer 32 ' cew_Error_Count [31:0] $end
$var integer 32 ( cew_Test_Count [31:0] $end
$var reg 1 ) t_P1 $end
$var reg 1 * t_P11 $end
$var reg 1 + t_P13 $end
$var reg 1 , t_P14 $end
$var reg 1 - t_P3 $end
$var reg 1 . t_P5 $end
$var reg 1 / t_P7 $end
$var reg 1 0 t_P9 $end
$scope module cut $end
$var wire 1 1 P1 $end
$var wire 1 2 P11 $end
$var wire 1 3 P13 $end
$var wire 1 4 P14 $end
$var wire 1 5 P3 $end
$var wire 1 6 P5 $end
$var wire 1 7 P7 $end
$var wire 1 8 P9 $end
$var reg 1 9 P10 $end
$var reg 1 : P12 $end
$var reg 1 ; P2 $end
$var reg 1 < P4 $end
$var reg 1 = P6 $end
$var reg 1 > P8 $end
$upscope $end
$upscope $end
$enddefinitions $end
#0
$dumpvars
x>
x=
x<
1;
x:
x9
x8
07
x6
x5
14
x3
x2
01
x0
0/
x.
x-
1,
x+
x*
0)
b1 (
b0 '
x&
x%
x$
1#
x"
x!
$end
#1
0;
0#
1)
11
b10 (
#2
1<
1$
0-
05
b11 (
#3
0<
0$
1-
15
b100 (
#4
1=
1%
0.
06
b101 (
#5
0=
0%
1.
16
b110 (
#6
1>
1&
00
08
b111 (
#7
0>
0&
10
18
b1000 (
#8
19
1!
0*
02
b1001 (
#9
09
0!
1*
12
b1010 (
#10
1:
1"
0+
03
b1011 (
#11
0:
0"
1+
13
b1100 (
