Assembly_VerilogAndLogicGates/TTL/sn7411/behaviour.v
//================================================================--
// Design Unit	: sn7411 (behaviour) 
//
// File Name	: behaviour.v
//
// Purpose	: model of TTL SN7411 triple and IC
//
// Dependences	: none
//
// Author	: Peter Walsh, Vancouver Island University
//
// Environmant	: Icarus
//-------------------------------------------------------------------
// Revision List	
// Version	Author	Date	Changes
// 1.0		PW	Sept 10 New version
//================================================================--

module sn7411 (P1, P2, P3, P4, P5, P6, P7, P8, P9, P10, P11, P12, P13, P14); 

   output P6, P8, P12;
   input P1, P2, P3, P4, P5, P7, P9, P10, P11, P13, P14;

   reg P6, P8, P12;

   always @(P3, P4, P5, P7, P14) begin

      if ((P14 == 1'b 1) && (P7 == 1'b 0)) begin
         P6 = P3 & P4 & P5;
      end  
   end

   always @(P7, P9, P10, P11, P14) begin

      if ((P14 == 1'b 1) && (P7 == 1'b 0)) begin
         P8 = P9 & P10 & P11;
      end  
   end

   always @(P1, P2, P7, P13, P14) begin

      if ((P14 == 1'b 1) && (P7 == 1'b 0)) begin
         P12 = P1 & P2 & P13;
      end  
   end

endmodule

Assembly_VerilogAndLogicGates/TTL/sn7411/tb.v
//================================================================--
// Design Unit  : cew testbench for sn7411
//
// File Name    : tb.cew
//
// Purpose      : design verification
//
// Note         :
//
// Limitations  :
//
// Errors       : none known
//
// Library      : sn7411 
//
// Dependences  : none
//
// Author       : Peter Walsh, Vancouver Island University
//
// System       : icarus (Linux)
//
//------------------------------------------------------------------
// Revision List
// Version      Author  Date    Changes
// 1.0          PW      Sep 10  New version
//================================================================--












module test_bench();

   integer cew_Test_Count=0;
          integer cew_Error_Count=0;

   wire t_P6, t_P8, t_P12;
   reg t_P1, t_P2, t_P3, t_P4, t_P5, t_P7, t_P9, t_P10, t_P11, t_P13, t_P14;
   integer i;

   // Gold function returns x and y and z
   function gold;
      input x;
      input y;
      input z;

      gold=(x&y&z);
   endfunction

   sn7411 cut(t_P1, t_P2, t_P3, t_P4, t_P5, t_P6, t_P7, t_P8, t_P9, t_P10, t_P11, t_P12, t_P13, t_P14);

   initial begin
      $dumpfile("test_bench.vcd");
      $dumpvars(0,test_bench);

      t_P14=1; t_P7=0;

      // note, gates are tested sequentially

      for (i=0; i<8; i=i+1)
         begin
         cew_Test_Count=cew_Test_Count+1;
          t_P1=i[2];t_P2=i[1];t_P13=i[0];#1;
          if ((t_P12) !== (gold(t_P1, t_P2, t_P13))) begin
             cew_Error_Count=cew_Error_Count+1;
             $display("\nTest Case ERROR (Ncase) in script at line number 59");
             $display("Actual Value is ", t_P12 );
             $display("Expected Value is ", gold(t_P1, t_P2, t_P13) );
          end

         cew_Test_Count=cew_Test_Count+1;
          t_P3=i[2];t_P4=i[1];t_P5=i[0];#1;
          if ((t_P6) !== (gold(t_P3, t_P4, t_P5))) begin
             cew_Error_Count=cew_Error_Count+1;
             $display("\nTest Case ERROR (Ncase) in script at line number 60");
             $display("Actual Value is ", t_P6 );
             $display("Expected Value is ", gold(t_P3, t_P4, t_P5) );
          end

         cew_Test_Count=cew_Test_Count+1;
          t_P9=i[2];t_P10=i[1];t_P11=i[0];#1;
          if ((t_P6) !== (gold(t_P3, t_P4, t_P5))) begin
             cew_Error_Count=cew_Error_Count+1;
             $display("\nTest Case ERROR (Ncase) in script at line number 61");
             $display("Actual Value is ", t_P6 );
             $display("Expected Value is ", gold(t_P3, t_P4, t_P5) );
          end

         end
      $display("\n**********Summary**********\n");
          $display("Total number of test cases = %d \n", cew_Test_Count);
          $display("Total number of test cases in error = %d \n", cew_Error_Count);

      #1 $finish();
   end

endmodule

Assembly_VerilogAndLogicGates/TTL/sn7411/test_bench.vcd
$date
	Tue Jun 16 21:59:09 2015
$end
$version
	Icarus Verilog
$end
$timescale
	1s
$end
$scope module test_bench $end
$var wire 1 ! t_P12 $end
$var wire 1 " t_P6 $end
$var wire 1 # t_P8 $end
$var integer 32 $ cew_Error_Count [31:0] $end
$var integer 32 % cew_Test_Count [31:0] $end
$var integer 32 & i [31:0] $end
$var reg 1 ' t_P1 $end
$var reg 1 ( t_P10 $end
$var reg 1 ) t_P11 $end
$var reg 1 * t_P13 $end
$var reg 1 + t_P14 $end
$var reg 1 , t_P2 $end
$var reg 1 - t_P3 $end
$var reg 1 . t_P4 $end
$var reg 1 / t_P5 $end
$var reg 1 0 t_P7 $end
$var reg 1 1 t_P9 $end
$scope function gold $end
$var reg 1 2 gold $end
$var reg 1 3 x $end
$var reg 1 4 y $end
$var reg 1 5 z $end
$upscope $end
$scope module cut $end
$var wire 1 6 P1 $end
$var wire 1 7 P10 $end
$var wire 1 8 P11 $end
$var wire 1 9 P13 $end
$var wire 1 : P14 $end
$var wire 1 ; P2 $end
$var wire 1 < P3 $end
$var wire 1 = P4 $end
$var wire 1 > P5 $end
$var wire 1 ? P7 $end
$var wire 1 @ P9 $end
$var reg 1 A P12 $end
$var reg 1 B P6 $end
$var reg 1 C P8 $end
$upscope $end
$upscope $end
$enddefinitions $end
#0
$dumpvars
xC
xB
0A
x@
0?
x>
x=
x<
0;
1:
09
x8
x7
06
x5
x4
x3
x2
x1
00
x/
x.
x-
0,
1+
0*
x)
x(
0'
b0 &
b1 %
b0 $
x#
x"
0!
$end
#1
0B
0"
0/
0>
0.
0=
0-
0<
b10 %
02
05
04
03
#2
0C
0#
0)
08
0(
07
01
0@
b11 %
#3
1*
19
b100 %
b1 &
#4
1/
1>
b101 %
15
#5
1)
18
b110 %
#6
0*
09
1,
1;
b111 %
b10 &
#7
0/
0>
1.
1=
b1000 %
05
14
#8
0)
08
1(
17
b1001 %
#9
1*
19
b1010 %
b11 &
#10
1/
1>
b1011 %
15
#11
1)
18
b1100 %
#12
0*
09
0,
0;
1'
16
b1101 %
b100 &
#13
0/
0>
0.
0=
1-
1<
b1110 %
05
04
13
#14
0)
08
0(
07
11
1@
b1111 %
#15
1*
19
b10000 %
b101 &
#16
1/
1>
b10001 %
15
#17
1)
18
b10010 %
#18
0*
09
1,
1;
b10011 %
b110 &
#19
0/
0>
1.
1=
b10100 %
05
14
#20
0)
08
1(
17
b10101 %
#21
1A
1!
1*
19
b10110 %
b111 &
#22
1B
1"
1/
1>
b10111 %
12
15
#23
1C
1#
1)
18
b11000 %
#24
b1000 &
