Assembly_VerilogAndLogicGates/TTL/sn7408/behaviour.v
//================================================================--
// Design Unit	: sn7408 (behaviour) 
//
// File Name	: behaviour.v
//
// Purpose	: model of TTL SN7408 quod and IC
//
// Author	: Peter Walsh, Vancouver Island University
//
// Environmant	: Icarus
//-------------------------------------------------------------------
// Revision List	
// Version	Author	Date	Changes
// 1.0		PW	Sept 10 New version
//================================================================--

module sn7408 (P1, P2, P3, P4, P5, P6, P7, P8, P9, P10, P11, P12, P13, P14); 

   output P3, P6, P8, P11;
   input P1, P2, P4, P5, P7, P9, P10, P12, P13, P14;

   reg P3, P6, P8, P11;

   always @(P1, P2, P7, P14) begin

      if ((P14 == 1'b 1) && (P7 == 1'b 0)) begin
         P3 = P1 & P2;
      end  
   end

   always @(P4, P5, P7, P14) begin

      if ((P14 == 1'b 1) && (P7 == 1'b 0)) begin
         P6 = P4 & P5;
      end  
   end

   always @(P7, P9, P10, P14) begin

      if ((P14 == 1'b 1) && (P7 == 1'b 0)) begin
         P8 = P9 & P10;
      end  
   end

   always @(P7, P12, P13, P14) begin

      if ((P14 == 1'b 1) && (P7 == 1'b 0)) begin
         P11 = P12 & P13;
      end  
   end

endmodule

Assembly_VerilogAndLogicGates/TTL/sn7408/tb.v
//================================================================--
// Design Unit  : cew testbench for sn7408
//
// File Name    : tb.cew
//
// Purpose      : design verification
//
// Note         :
//
// Limitations  :
//
// Errors       : none known
//
// Library      : sn7408 
//
// Dependences  : none
//
// Author       : Peter Walsh, Vancouver Island University
//
// System       : icarus (Linux)
//
//------------------------------------------------------------------
// Revision List
// Version      Author  Date    Changes
// 1.0          PW      Sep 10  New version
//================================================================--












module test_bench();

   integer cew_Test_Count=0;
          integer cew_Error_Count=0;

   wire t_P3, t_P6, t_P8, t_P11;
   reg t_P1, t_P2, t_P4, t_P5, t_P7, t_P9, t_P10, t_P12, t_P13, t_P14;

   sn7408 cut(t_P1, t_P2, t_P3, t_P4, t_P5, t_P6, t_P7, t_P8, t_P9, t_P10, t_P11, t_P12, t_P13, t_P14);

   initial begin
      $dumpfile("test_bench.vcd");
      $dumpvars(0,test_bench);

      t_P14=1; t_P7=0;

      // note, gates are tested sequentially

      cew_Test_Count=cew_Test_Count+1;
          t_P1=0;t_P2=0;#1;
          if ((t_P3) !== (0)) begin
             cew_Error_Count=cew_Error_Count+1;
             $display("\nTest Case ERROR (Ncase) in script at line number 47");
             $display("Actual Value is ", t_P3 );
             $display("Expected Value is ", 0 );
          end

      cew_Test_Count=cew_Test_Count+1;
          t_P1=0;t_P2=1;#1;
          if ((t_P3) !== (0)) begin
             cew_Error_Count=cew_Error_Count+1;
             $display("\nTest Case ERROR (Ncase) in script at line number 48");
             $display("Actual Value is ", t_P3 );
             $display("Expected Value is ", 0 );
          end

      cew_Test_Count=cew_Test_Count+1;
          t_P1=1;t_P2=0;#1;
          if ((t_P3) !== (0)) begin
             cew_Error_Count=cew_Error_Count+1;
             $display("\nTest Case ERROR (Ncase) in script at line number 49");
             $display("Actual Value is ", t_P3 );
             $display("Expected Value is ", 0 );
          end

      cew_Test_Count=cew_Test_Count+1;
          t_P1=1;t_P2=1;#1;
          if ((t_P3) !== (1)) begin
             cew_Error_Count=cew_Error_Count+1;
             $display("\nTest Case ERROR (Ncase) in script at line number 50");
             $display("Actual Value is ", t_P3 );
             $display("Expected Value is ", 1 );
          end


      cew_Test_Count=cew_Test_Count+1;
          t_P4=0;t_P5=0;#1;
          if ((t_P6) !== (0)) begin
             cew_Error_Count=cew_Error_Count+1;
             $display("\nTest Case ERROR (Ncase) in script at line number 52");
             $display("Actual Value is ", t_P6 );
             $display("Expected Value is ", 0 );
          end

      cew_Test_Count=cew_Test_Count+1;
          t_P4=0;t_P5=1;#1;
          if ((t_P6) !== (0)) begin
             cew_Error_Count=cew_Error_Count+1;
             $display("\nTest Case ERROR (Ncase) in script at line number 53");
             $display("Actual Value is ", t_P6 );
             $display("Expected Value is ", 0 );
          end

      cew_Test_Count=cew_Test_Count+1;
          t_P4=1;t_P5=0;#1;
          if ((t_P6) !== (0)) begin
             cew_Error_Count=cew_Error_Count+1;
             $display("\nTest Case ERROR (Ncase) in script at line number 54");
             $display("Actual Value is ", t_P6 );
             $display("Expected Value is ", 0 );
          end

      cew_Test_Count=cew_Test_Count+1;
          t_P4=1;t_P5=1;#1;
          if ((t_P6) !== (1)) begin
             cew_Error_Count=cew_Error_Count+1;
             $display("\nTest Case ERROR (Ncase) in script at line number 55");
             $display("Actual Value is ", t_P6 );
             $display("Expected Value is ", 1 );
          end


      cew_Test_Count=cew_Test_Count+1;
          t_P9=0;t_P10=0;#1;
          if ((t_P8) !== (0)) begin
             cew_Error_Count=cew_Error_Count+1;
             $display("\nTest Case ERROR (Ncase) in script at line number 57");
             $display("Actual Value is ", t_P8 );
             $display("Expected Value is ", 0 );
          end

      cew_Test_Count=cew_Test_Count+1;
          t_P9=0;t_P10=1;#1;
          if ((t_P8) !== (0)) begin
             cew_Error_Count=cew_Error_Count+1;
             $display("\nTest Case ERROR (Ncase) in script at line number 58");
             $display("Actual Value is ", t_P8 );
             $display("Expected Value is ", 0 );
          end

      cew_Test_Count=cew_Test_Count+1;
          t_P9=1;t_P10=0;#1;
          if ((t_P8) !== (0)) begin
             cew_Error_Count=cew_Error_Count+1;
             $display("\nTest Case ERROR (Ncase) in script at line number 59");
             $display("Actual Value is ", t_P8 );
             $display("Expected Value is ", 0 );
          end

      cew_Test_Count=cew_Test_Count+1;
          t_P9=1;t_P10=1;#1;
          if ((t_P8) !== (1)) begin
             cew_Error_Count=cew_Error_Count+1;
             $display("\nTest Case ERROR (Ncase) in script at line number 60");
             $display("Actual Value is ", t_P8 );
             $display("Expected Value is ", 1 );
          end


      cew_Test_Count=cew_Test_Count+1;
          t_P13=0;t_P12=0;#1;
          if ((t_P11) !== (0)) begin
             cew_Error_Count=cew_Error_Count+1;
             $display("\nTest Case ERROR (Ncase) in script at line number 62");
             $display("Actual Value is ", t_P11 );
             $display("Expected Value is ", 0 );
          end

      cew_Test_Count=cew_Test_Count+1;
          t_P13=0;t_P12=1;#1;
          if ((t_P11) !== (0)) begin
             cew_Error_Count=cew_Error_Count+1;
             $display("\nTest Case ERROR (Ncase) in script at line number 63");
             $display("Actual Value is ", t_P11 );
             $display("Expected Value is ", 0 );
          end

      cew_Test_Count=cew_Test_Count+1;
          t_P13=1;t_P12=0;#1;
          if ((t_P11) !== (0)) begin
             cew_Error_Count=cew_Error_Count+1;
             $display("\nTest Case ERROR (Ncase) in script at line number 64");
             $display("Actual Value is ", t_P11 );
             $display("Expected Value is ", 0 );
          end

      cew_Test_Count=cew_Test_Count+1;
          t_P13=1;t_P12=1;#1;
          if ((t_P11) !== (1)) begin
             cew_Error_Count=cew_Error_Count+1;
             $display("\nTest Case ERROR (Ncase) in script at line number 65");
             $display("Actual Value is ", t_P11 );
             $display("Expected Value is ", 1 );
          end


      $display("\n**********Summary**********\n");
          $display("Total number of test cases = %d \n", cew_Test_Count);
          $display("Total number of test cases in error = %d \n", cew_Error_Count);

      #1 $finish();
   end

endmodule

Assembly_VerilogAndLogicGates/TTL/sn7408/test_bench.vcd
$date
	Wed Oct 30 17:06:36 2013
$end
$version
	Icarus Verilog
$end
$timescale
	1s
$end
$scope module test_bench $end
$var wire 1 ! t_P11 $end
$var wire 1 " t_P3 $end
$var wire 1 # t_P6 $end
$var wire 1 $ t_P8 $end
$var integer 32 % cew_Error_Count [31:0] $end
$var integer 32 & cew_Test_Count [31:0] $end
$var reg 1 ' t_P1 $end
$var reg 1 ( t_P10 $end
$var reg 1 ) t_P12 $end
$var reg 1 * t_P13 $end
$var reg 1 + t_P14 $end
$var reg 1 , t_P2 $end
$var reg 1 - t_P4 $end
$var reg 1 . t_P5 $end
$var reg 1 / t_P7 $end
$var reg 1 0 t_P9 $end
$scope module cut $end
$var wire 1 1 P1 $end
$var wire 1 2 P10 $end
$var wire 1 3 P12 $end
$var wire 1 4 P13 $end
$var wire 1 5 P14 $end
$var wire 1 6 P2 $end
$var wire 1 7 P4 $end
$var wire 1 8 P5 $end
$var wire 1 9 P7 $end
$var wire 1 : P9 $end
$var reg 1 ; P11 $end
$var reg 1 < P3 $end
$var reg 1 = P6 $end
$var reg 1 > P8 $end
$upscope $end
$upscope $end
$enddefinitions $end
#0
$dumpvars
x>
x=
0<
x;
x:
09
x8
x7
06
15
x4
x3
x2
01
x0
0/
x.
x-
0,
1+
x*
x)
x(
0'
b1 &
b0 %
x$
x#
0"
x!
$end
#1
1,
16
b10 &
#2
0,
06
1'
11
b11 &
#3
1<
1"
1,
16
b100 &
#4
0=
0#
0.
08
0-
07
b101 &
#5
1.
18
b110 &
#6
0.
08
1-
17
b111 &
#7
1=
1#
1.
18
b1000 &
#8
0>
0$
0(
02
00
0:
b1001 &
#9
1(
12
b1010 &
#10
0(
02
10
1:
b1011 &
#11
1>
1$
1(
12
b1100 &
#12
0;
0!
0)
03
0*
04
b1101 &
#13
1)
13
b1110 &
#14
0)
03
1*
14
b1111 &
#15
1;
1!
1)
13
b10000 &
