Assembly_VerilogAndLogicGates/TTL/sn7400/behaviour.v
//================================================================--
// Design Unit	: sn7400 (behaviour) 
//
// File Name	: behaviour.v
//
// Purpose	: model of TTL SN7400 quod nand IC
//
// Dependences	: none
//
// Author	: Peter Walsh, Vancouver Island University
//
// Environmant	: Icarus
//-------------------------------------------------------------------
// Revision List	
// Version	Author	Date	Changes
// 1.0		PW	Sept 10 New version
//================================================================--

module sn7400 (P1, P2, P3, P4, P5, P6, P7, P8, P9, P10, P11, P12, P13, P14); 

   output P3, P6, P8, P11;
   input P1, P2, P4, P5, P7, P9, P10, P12, P13, P14;

   reg P3, P6, P8, P11;

   always @(P1, P2, P7, P14) begin

      if ((P14 == 1'b 1) && (P7 == 1'b 0)) begin
         P3 = P1 ~& P2;
      end  
      
   end

   always @(P4, P5, P7, P14) begin

      if ((P14 == 1'b 1) && (P7 == 1'b 0)) begin
         P6 = P4 ~& P5;
      end  
      
   end

   always @(P7, P9, P10, P14) begin

      if ((P14 == 1'b 1) && (P7 == 1'b 0)) begin
         P8 = P9 ~& P10;
      end  
      
   end

   always @(P7, P12, P13, P14) begin

      if ((P14 == 1'b 1) && (P7 == 1'b 0)) begin
         P11 = P12 ~& P13;
      end  
      
   end


endmodule

Assembly_VerilogAndLogicGates/TTL/sn7400/tb.v
//================================================================--
// Design Unit  : cew testbench for sn7400
//
// File Name    : tb.cew
//
// Purpose      : design verification
//
// Note         :
//
// Limitations  :
//
// Errors       : none known
//
// Library      : sn7400 
//
// Dependences  : none
//
// Author       : Peter Walsh, Vancouver Island University
//
// System       : icarus (Linux)
//
//------------------------------------------------------------------
// Revision List
// Version      Author  Date    Changes
// 1.0          PW      Sep 10  New version
//================================================================--















module test_bench();

   integer cew_Test_Count=0;
          integer cew_Error_Count=0;

   wire t_P3, t_P6, t_P8, t_P11;
   reg t_P1, t_P2, t_P4, t_P5, t_P9, t_P10, t_P12, t_P13;
   supply1 t_P14;
   supply0 t_P7;
   integer i;

   // Gold function returns x nand y
   function gold;
      input x;
      input y;

      gold=(x~&y);
   endfunction

   sn7400 cut(t_P1, t_P2, t_P3, t_P4, t_P5, t_P6, t_P7, t_P8, t_P9, t_P10, t_P11, t_P12, t_P13, t_P14);

   initial begin
      $dumpfile("test_bench.vcd");
      $dumpvars(0,test_bench);

      // note, gates are tested sequentially
      // also, 3 different styles of testing are shown


      // style 1 .. explicit enumeration
      cew_Test_Count=cew_Test_Count+1;
          t_P1=0;t_P2=0;#1;
          if ((t_P3) !== (t_P1 ~& t_P2)) begin
             cew_Error_Count=cew_Error_Count+1;
             $display("\nTest Case ERROR (Ncase) in script at line number 59");
             $display("Actual Value is ", t_P3 );
             $display("Expected Value is ", t_P1 ~& t_P2 );
          end

      cew_Test_Count=cew_Test_Count+1;
          t_P1=0;t_P2=1;#1;
          if ((t_P3) !== (t_P1 ~& t_P2)) begin
             cew_Error_Count=cew_Error_Count+1;
             $display("\nTest Case ERROR (Ncase) in script at line number 60");
             $display("Actual Value is ", t_P3 );
             $display("Expected Value is ", t_P1 ~& t_P2 );
          end

      cew_Test_Count=cew_Test_Count+1;
          t_P1=1;t_P2=0;#1;
          if ((t_P3) !== (t_P1 ~& t_P2)) begin
             cew_Error_Count=cew_Error_Count+1;
             $display("\nTest Case ERROR (Ncase) in script at line number 61");
             $display("Actual Value is ", t_P3 );
             $display("Expected Value is ", t_P1 ~& t_P2 );
          end

      cew_Test_Count=cew_Test_Count+1;
          t_P1=1;t_P2=1;#1;
          if ((t_P3) !== (t_P1 ~& t_P2)) begin
             cew_Error_Count=cew_Error_Count+1;
             $display("\nTest Case ERROR (Ncase) in script at line number 62");
             $display("Actual Value is ", t_P3 );
             $display("Expected Value is ", t_P1 ~& t_P2 );
          end


      // style 2 .. explicit enumeration with a gold function (oracal)
      cew_Test_Count=cew_Test_Count+1;
          t_P4=0;t_P5=0;#1;
          if ((t_P6) !== (gold(t_P4, t_P5))) begin
             cew_Error_Count=cew_Error_Count+1;
             $display("\nTest Case ERROR (Ncase) in script at line number 65");
             $display("Actual Value is ", t_P6 );
             $display("Expected Value is ", gold(t_P4, t_P5) );
          end

      cew_Test_Count=cew_Test_Count+1;
          t_P4=0;t_P5=1;#1;
          if ((t_P6) !== (gold(t_P4, t_P5))) begin
             cew_Error_Count=cew_Error_Count+1;
             $display("\nTest Case ERROR (Ncase) in script at line number 66");
             $display("Actual Value is ", t_P6 );
             $display("Expected Value is ", gold(t_P4, t_P5) );
          end

      cew_Test_Count=cew_Test_Count+1;
          t_P4=1;t_P5=0;#1;
          if ((t_P6) !== (gold(t_P4, t_P5))) begin
             cew_Error_Count=cew_Error_Count+1;
             $display("\nTest Case ERROR (Ncase) in script at line number 67");
             $display("Actual Value is ", t_P6 );
             $display("Expected Value is ", gold(t_P4, t_P5) );
          end

      cew_Test_Count=cew_Test_Count+1;
          t_P4=1;t_P5=1;#1;
          if ((t_P6) !== (gold(t_P4, t_P5))) begin
             cew_Error_Count=cew_Error_Count+1;
             $display("\nTest Case ERROR (Ncase) in script at line number 68");
             $display("Actual Value is ", t_P6 );
             $display("Expected Value is ", gold(t_P4, t_P5) );
          end


      // style 3 .. implicit enumeration with a gold function (oracal)
      for (i=0; i<4; i=i+1)
        begin
        cew_Test_Count=cew_Test_Count+1;
          t_P9=i[1];t_P10=i[0];#1;
          if ((t_P8) !== (gold(t_P9, t_P10))) begin
             cew_Error_Count=cew_Error_Count+1;
             $display("\nTest Case ERROR (Ncase) in script at line number 73");
             $display("Actual Value is ", t_P8 );
             $display("Expected Value is ", gold(t_P9, t_P10) );
          end

        cew_Test_Count=cew_Test_Count+1;
          t_P13=i[1];t_P12=i[0];#1;
          if ((t_P11) !== (gold(t_P13, t_P12))) begin
             cew_Error_Count=cew_Error_Count+1;
             $display("\nTest Case ERROR (Ncase) in script at line number 74");
             $display("Actual Value is ", t_P11 );
             $display("Expected Value is ", gold(t_P13, t_P12) );
          end

        end
 
      $display("\n**********Summary**********\n");
          $display("Total number of test cases = %d \n", cew_Test_Count);
          $display("Total number of test cases in error = %d \n", cew_Error_Count);

      #1 $finish();
   end

endmodule

Assembly_VerilogAndLogicGates/TTL/sn7400/test_bench.vcd
$date
	Thu Sep 14 16:41:30 2017
$end
$version
	Icarus Verilog
$end
$timescale
	1s
$end
$scope module test_bench $end
$var wire 1 ! t_P14 $end
$var wire 1 " t_P7 $end
$var wire 1 # t_P8 $end
$var wire 1 $ t_P6 $end
$var wire 1 % t_P3 $end
$var wire 1 & t_P11 $end
$var reg 1 ' t_P1 $end
$var reg 1 ( t_P10 $end
$var reg 1 ) t_P12 $end
$var reg 1 * t_P13 $end
$var reg 1 + t_P2 $end
$var reg 1 , t_P4 $end
$var reg 1 - t_P5 $end
$var reg 1 . t_P9 $end
$var integer 32 / cew_Error_Count [31:0] $end
$var integer 32 0 cew_Test_Count [31:0] $end
$var integer 32 1 i [31:0] $end
$scope function gold $end
$var reg 1 2 gold $end
$var reg 1 3 x $end
$var reg 1 4 y $end
$upscope $end
$scope module cut $end
$var wire 1 ' P1 $end
$var wire 1 ( P10 $end
$var wire 1 ) P12 $end
$var wire 1 * P13 $end
$var wire 1 ! P14 $end
$var wire 1 + P2 $end
$var wire 1 , P4 $end
$var wire 1 - P5 $end
$var wire 1 " P7 $end
$var wire 1 . P9 $end
$var reg 1 & P11 $end
$var reg 1 % P3 $end
$var reg 1 $ P6 $end
$var reg 1 # P8 $end
$upscope $end
$upscope $end
$enddefinitions $end
#0
$dumpvars
x4
x3
x2
bx 1
b1 0
b0 /
x.
x-
x,
0+
x*
x)
x(
0'
x&
1%
x$
x#
0"
1!
$end
#1
1+
b10 0
#2
0+
1'
b11 0
#3
0%
1+
b100 0
#4
1$
0-
0,
b101 0
#5
1-
b110 0
12
03
04
#6
0-
1,
b111 0
14
#7
0$
1-
b1000 0
13
04
#8
1#
0(
0.
b1001 0
b0 1
02
14
#9
1&
0)
0*
b1010 0
12
03
04
#10
1(
b1011 0
b1 1
#11
1)
b1100 0
14
#12
0(
1.
b1101 0
b10 1
#13
0)
1*
b1110 0
13
04
#14
0#
1(
b1111 0
b11 1
#15
0&
1)
b10000 0
02
14
#16
b100 1
