Assembly_VerilogAndLogicGates/TTL/sn7476/behaviour.v
//================================================================--
// Design Unit	: sn7476 (behaviour) 
//
// File Name	: behaviour.v
//
// Purpose	: model of TTL SN7476 dual negative master-slave FF IC
//
// Author	: Peter Walsh, Vancouver Island University
//
// Environmant	: Icarus
//-------------------------------------------------------------------
// Revision List	
// Version	Author	Date	Changes
// 1.0		PW	Sept 10 New version
//================================================================--

module sn7476 (P1, P2, P3, P4, P5, P6, P7, P8, P9, P10, P11, P12, P13, P14, P15, P16); 

   output reg P10, P11, P14, P15;
   input P1, P2, P3, P4, P5, P6, P7, P8, P9, P12, P13, P16;

   reg master1, master2;

   // FF #1 
   always @ (P2, P3, P1, P4, P16) begin
      if ((P5 == 1'b 1) && (P13 == 1'b 0)) begin
         // async operation
         if (P2 == 1'b 0) begin // assume P3==1
            P15<=1'b 1;
            P14<=1'b 0;
            master1<=1;
         end else if (P3 == 1'b 0) begin //assume P2==1
            P15<=1'b 0;
            P14<=1'b 1;
            master1<=0;
         end else if (P1 == 1'b 1) begin // sync operation
            if ((P16 == 1'b 1) && (P4 == 1'b 0)) 
               master1<=0;
            else if  ((P16 == 1'b 0) && (P4 == 1'b 1)) 
               master1<=1;
            else if ((P16 == 1'b 1) && (P4 == 1'b 1)) 
               master1<=P14;
         end else begin
            P15<=master1;
            P14<=~master1;
         end
      end
   end

   // FF #2 
   always @ (P7, P8, P6, P9, P12) begin
      if ((P5 == 1'b 1) && (P13 == 1'b 0)) begin
         // async operation
         if (P7 == 1'b 0) begin // assume P8==1
            P11<=1'b 1;
            P10<=1'b 0;
            master2<=1;
         end else if (P8 == 1'b 0) begin //assume P7==1
            P11<=1'b 0;
            P10<=1'b 1;
            master2<=0;
         end else if (P6 == 1'b 1) begin // sync operation
            if ((P12 == 1'b 1) && (P9 == 1'b 0)) 
               master2<=0;
            else if  ((P12 == 1'b 0) && (P9 == 1'b 1))
               master2<=1;
            else if ((P12 == 1'b 1) && (P9 == 1'b 1)) 
               master2<=P10;
         end else begin
            P11<=master2;
            P10<=~master2;
         end
      end
   end


endmodule

Assembly_VerilogAndLogicGates/TTL/sn7476/tb.v
//================================================================--
// Design Unit  : cew testbench for sn7476
//
// File Name    : tb.cew
//
// Purpose      : design verification
//
// Author       : Peter Walsh, Vancouver Island University
//
// System       : icarus (Linux)
//
//------------------------------------------------------------------
// Revision List
// Version      Author  Date    Changes
// 1.0          PW      Sep 10  New version
//================================================================--











module test_bench();

   integer cew_Test_Count=0;
          integer cew_Error_Count=0;

   wire t_P10, t_P11, t_P14, t_P15;
   reg t_P1, t_P2, t_P3, t_P4, t_P5, t_P6, t_P7, t_P8, t_P9, t_P12, t_P13, t_P16;

   sn7476 cut(t_P1, t_P2, t_P3, t_P4, t_P5, t_P6, t_P7, t_P8, t_P9, t_P10, t_P11, t_P12, t_P13, t_P14, t_P15, t_P16);

   task clockTick1; // nasty syntax but task body can only be one (compound) statement
      begin
         t_P1=0; #3;
         t_P1=1; #6;
         t_P1=0; #3;
      end
   endtask

   task clockTick2; 
      begin
         t_P6=0; #3;
         t_P6=1; #6;
         t_P6=0; #3;
      end
   endtask

   initial begin
      $dumpfile("test_bench.vcd");
      $dumpvars(0,test_bench);

      t_P5=1; t_P13=0; #1;

      // Async Operation

      cew_Test_Count=cew_Test_Count+1;
          t_P2=0; t_P3=1; #1;
          if ((t_P15) !== (1)) begin
             cew_Error_Count=cew_Error_Count+1;
             $display("\nTest Case ERROR (Ncase) in script at line number 52");
             $display("Actual Value is ", t_P15 );
             $display("Expected Value is ", 1 );
          end

      cew_Test_Count=cew_Test_Count+1;
          t_P2=1; t_P3=0; #1;
          if ((t_P15) !== (0)) begin
             cew_Error_Count=cew_Error_Count+1;
             $display("\nTest Case ERROR (Ncase) in script at line number 53");
             $display("Actual Value is ", t_P15 );
             $display("Expected Value is ", 0 );
          end

      cew_Test_Count=cew_Test_Count+1;
          t_P2=1; t_P3=1; #1;
          if ((t_P15) !== (0)) begin
             cew_Error_Count=cew_Error_Count+1;
             $display("\nTest Case ERROR (Ncase) in script at line number 54");
             $display("Actual Value is ", t_P15 );
             $display("Expected Value is ", 0 );
          end

     
      cew_Test_Count=cew_Test_Count+1;
          t_P7=0; t_P8=1; #1;
          if ((t_P11) !== (1)) begin
             cew_Error_Count=cew_Error_Count+1;
             $display("\nTest Case ERROR (Ncase) in script at line number 56");
             $display("Actual Value is ", t_P11 );
             $display("Expected Value is ", 1 );
          end

      cew_Test_Count=cew_Test_Count+1;
          t_P7=1; t_P8=0; #1;
          if ((t_P11) !== (0)) begin
             cew_Error_Count=cew_Error_Count+1;
             $display("\nTest Case ERROR (Ncase) in script at line number 57");
             $display("Actual Value is ", t_P11 );
             $display("Expected Value is ", 0 );
          end

      cew_Test_Count=cew_Test_Count+1;
          t_P7=1; t_P8=1; #1;
          if ((t_P11) !== (0)) begin
             cew_Error_Count=cew_Error_Count+1;
             $display("\nTest Case ERROR (Ncase) in script at line number 58");
             $display("Actual Value is ", t_P11 );
             $display("Expected Value is ", 0 );
          end


      // Normal Operation

      cew_Test_Count=cew_Test_Count+1;
          t_P16=1;t_P4=0;clockTick1();
          if ((t_P15) !== (0)) begin
             cew_Error_Count=cew_Error_Count+1;
             $display("\nTest Case ERROR (Ncase) in script at line number 62");
             $display("Actual Value is ", t_P15 );
             $display("Expected Value is ", 0 );
          end

      cew_Test_Count=cew_Test_Count+1;
          
          if ((t_P14) !== (1)) begin
             cew_Error_Count=cew_Error_Count+1;
             $display("\nTest Case ERROR (Ncase) in script at line number 63");
             $display("Actual Value is ", t_P14 );
             $display("Expected Value is ", 1 );
          end

      cew_Test_Count=cew_Test_Count+1;
          t_P16=0;t_P4=1;clockTick1();
          if ((t_P15) !== (1)) begin
             cew_Error_Count=cew_Error_Count+1;
             $display("\nTest Case ERROR (Ncase) in script at line number 64");
             $display("Actual Value is ", t_P15 );
             $display("Expected Value is ", 1 );
          end

      cew_Test_Count=cew_Test_Count+1;
          
          if ((t_P14) !== (0)) begin
             cew_Error_Count=cew_Error_Count+1;
             $display("\nTest Case ERROR (Ncase) in script at line number 65");
             $display("Actual Value is ", t_P14 );
             $display("Expected Value is ", 0 );
          end

      cew_Test_Count=cew_Test_Count+1;
          t_P16=0;t_P4=0;clockTick1();
          if ((t_P15) !== (1)) begin
             cew_Error_Count=cew_Error_Count+1;
             $display("\nTest Case ERROR (Ncase) in script at line number 66");
             $display("Actual Value is ", t_P15 );
             $display("Expected Value is ", 1 );
          end

      cew_Test_Count=cew_Test_Count+1;
          
          if ((t_P14) !== (0)) begin
             cew_Error_Count=cew_Error_Count+1;
             $display("\nTest Case ERROR (Ncase) in script at line number 67");
             $display("Actual Value is ", t_P14 );
             $display("Expected Value is ", 0 );
          end

      cew_Test_Count=cew_Test_Count+1;
          t_P16=1;t_P4=1;clockTick1();
          if ((t_P15) !== (0)) begin
             cew_Error_Count=cew_Error_Count+1;
             $display("\nTest Case ERROR (Ncase) in script at line number 68");
             $display("Actual Value is ", t_P15 );
             $display("Expected Value is ", 0 );
          end

      cew_Test_Count=cew_Test_Count+1;
          
          if ((t_P14) !== (1)) begin
             cew_Error_Count=cew_Error_Count+1;
             $display("\nTest Case ERROR (Ncase) in script at line number 69");
             $display("Actual Value is ", t_P14 );
             $display("Expected Value is ", 1 );
          end

      
      cew_Test_Count=cew_Test_Count+1;
          t_P12=1;t_P9=0;clockTick2();
          if ((t_P11) !== (0)) begin
             cew_Error_Count=cew_Error_Count+1;
             $display("\nTest Case ERROR (Ncase) in script at line number 71");
             $display("Actual Value is ", t_P11 );
             $display("Expected Value is ", 0 );
          end

      cew_Test_Count=cew_Test_Count+1;
          
          if ((t_P10) !== (1)) begin
             cew_Error_Count=cew_Error_Count+1;
             $display("\nTest Case ERROR (Ncase) in script at line number 72");
             $display("Actual Value is ", t_P10 );
             $display("Expected Value is ", 1 );
          end

      cew_Test_Count=cew_Test_Count+1;
          t_P12=0;t_P9=1;clockTick2();
          if ((t_P11) !== (1)) begin
             cew_Error_Count=cew_Error_Count+1;
             $display("\nTest Case ERROR (Ncase) in script at line number 73");
             $display("Actual Value is ", t_P11 );
             $display("Expected Value is ", 1 );
          end

      cew_Test_Count=cew_Test_Count+1;
          
          if ((t_P10) !== (0)) begin
             cew_Error_Count=cew_Error_Count+1;
             $display("\nTest Case ERROR (Ncase) in script at line number 74");
             $display("Actual Value is ", t_P10 );
             $display("Expected Value is ", 0 );
          end

      cew_Test_Count=cew_Test_Count+1;
          t_P12=0;t_P9=0;clockTick2();
          if ((t_P11) !== (1)) begin
             cew_Error_Count=cew_Error_Count+1;
             $display("\nTest Case ERROR (Ncase) in script at line number 75");
             $display("Actual Value is ", t_P11 );
             $display("Expected Value is ", 1 );
          end

      cew_Test_Count=cew_Test_Count+1;
          
          if ((t_P10) !== (0)) begin
             cew_Error_Count=cew_Error_Count+1;
             $display("\nTest Case ERROR (Ncase) in script at line number 76");
             $display("Actual Value is ", t_P10 );
             $display("Expected Value is ", 0 );
          end

      cew_Test_Count=cew_Test_Count+1;
          t_P12=1;t_P9=1;clockTick2();
          if ((t_P11) !== (0)) begin
             cew_Error_Count=cew_Error_Count+1;
             $display("\nTest Case ERROR (Ncase) in script at line number 77");
             $display("Actual Value is ", t_P11 );
             $display("Expected Value is ", 0 );
          end

      cew_Test_Count=cew_Test_Count+1;
          
          if ((t_P10) !== (1)) begin
             cew_Error_Count=cew_Error_Count+1;
             $display("\nTest Case ERROR (Ncase) in script at line number 78");
             $display("Actual Value is ", t_P10 );
             $display("Expected Value is ", 1 );
          end


      // ones catching

      cew_Test_Count=cew_Test_Count+1;
          t_P2=1; t_P3=0; #1;
          if ((t_P15) !== (0)) begin
             cew_Error_Count=cew_Error_Count+1;
             $display("\nTest Case ERROR (Ncase) in script at line number 82");
             $display("Actual Value is ", t_P15 );
             $display("Expected Value is ", 0 );
          end

      cew_Test_Count=cew_Test_Count+1;
          t_P2=1; t_P3=1; #1;
          if ((t_P15) !== (0)) begin
             cew_Error_Count=cew_Error_Count+1;
             $display("\nTest Case ERROR (Ncase) in script at line number 83");
             $display("Actual Value is ", t_P15 );
             $display("Expected Value is ", 0 );
          end

      cew_Test_Count=cew_Test_Count+1;
          t_P16=0;t_P4=1;clockTick1();
          if ((t_P15) !== (1)) begin
             cew_Error_Count=cew_Error_Count+1;
             $display("\nTest Case ERROR (Ncase) in script at line number 84");
             $display("Actual Value is ", t_P15 );
             $display("Expected Value is ", 1 );
          end

      cew_Test_Count=cew_Test_Count+1;
          t_P16=0;t_P4=0;clockTick1();
          if ((t_P15) !== (1)) begin
             cew_Error_Count=cew_Error_Count+1;
             $display("\nTest Case ERROR (Ncase) in script at line number 85");
             $display("Actual Value is ", t_P15 );
             $display("Expected Value is ", 1 );
          end

      t_P1=1; #1;
      t_P16=1; #1;
      t_P16=0; #1;
      t_P1=0; #1;
      cew_Test_Count=cew_Test_Count+1;
          
          if ((t_P15) !== (0)) begin
             cew_Error_Count=cew_Error_Count+1;
             $display("\nTest Case ERROR (Ncase) in script at line number 90");
             $display("Actual Value is ", t_P15 );
             $display("Expected Value is ", 0 );
          end




      $display("\n**********Summary**********\n");
          $display("Total number of test cases = %d \n", cew_Test_Count);
          $display("Total number of test cases in error = %d \n", cew_Error_Count);

      #10 $finish();
   end

endmodule

Assembly_VerilogAndLogicGates/TTL/sn7476/test_bench.vcd
$date
	Thu Nov 21 15:50:41 2013
$end
$version
	Icarus Verilog
$end
$timescale
	1s
$end
$scope module test_bench $end
$var wire 1 ! t_P10 $end
$var wire 1 " t_P11 $end
$var wire 1 # t_P14 $end
$var wire 1 $ t_P15 $end
$var integer 32 % cew_Error_Count [31:0] $end
$var integer 32 & cew_Test_Count [31:0] $end
$var reg 1 ' t_P1 $end
$var reg 1 ( t_P12 $end
$var reg 1 ) t_P13 $end
$var reg 1 * t_P16 $end
$var reg 1 + t_P2 $end
$var reg 1 , t_P3 $end
$var reg 1 - t_P4 $end
$var reg 1 . t_P5 $end
$var reg 1 / t_P6 $end
$var reg 1 0 t_P7 $end
$var reg 1 1 t_P8 $end
$var reg 1 2 t_P9 $end
$scope module cut $end
$var wire 1 3 P1 $end
$var wire 1 4 P12 $end
$var wire 1 5 P13 $end
$var wire 1 6 P16 $end
$var wire 1 7 P2 $end
$var wire 1 8 P3 $end
$var wire 1 9 P4 $end
$var wire 1 : P5 $end
$var wire 1 ; P6 $end
$var wire 1 < P7 $end
$var wire 1 = P8 $end
$var wire 1 > P9 $end
$var reg 1 ? P10 $end
$var reg 1 @ P11 $end
$var reg 1 A P14 $end
$var reg 1 B P15 $end
$var reg 1 C master1 $end
$var reg 1 D master2 $end
$upscope $end
$scope task clockTick1 $end
$upscope $end
$scope task clockTick2 $end
$upscope $end
$upscope $end
$enddefinitions $end
#0
$dumpvars
xD
xC
xB
xA
x@
x?
x>
x=
x<
x;
1:
x9
x8
x7
x6
05
x4
x3
x2
x1
x0
x/
1.
x-
x,
x+
x*
0)
x(
x'
b0 &
b0 %
x$
x#
x"
x!
$end
#1
1C
0A
0#
1B
1$
1,
18
0+
07
b1 &
#2
0C
1A
1#
0B
0$
0,
08
1+
17
b10 &
#3
1,
18
b11 &
#4
1D
0?
0!
1@
1"
11
1=
00
0<
b100 &
#5
0D
1?
1!
0@
0"
01
0=
10
1<
b101 &
#6
11
1=
b110 &
#7
0'
03
0-
09
1*
16
b111 &
#10
1'
13
#16
0'
03
#19
1-
19
0*
06
b1001 &
#22
1C
1'
13
#28
0A
0#
1B
1$
0'
03
#31
0-
09
b1011 &
#34
1'
13
#40
0'
03
#43
1-
19
1*
16
b1101 &
#46
0C
1'
13
#52
1A
1#
0B
0$
0'
03
#55
0/
0;
02
0>
1(
14
b1111 &
#58
1/
1;
#64
0/
0;
#67
12
1>
0(
04
b10001 &
#70
1D
1/
1;
#76
0?
0!
1@
1"
0/
0;
#79
02
0>
b10011 &
#82
1/
1;
#88
0/
0;
#91
12
1>
1(
14
b10101 &
#94
0D
1/
1;
#100
1?
1!
0@
0"
0/
0;
#103
0,
08
b10111 &
#104
1,
18
b11000 &
#105
0*
06
b11001 &
#108
1C
1'
13
#114
0A
0#
1B
1$
0'
03
#117
0-
09
b11010 &
#120
1'
13
#126
0'
03
#129
1'
13
#130
0C
1*
16
#131
0*
06
#132
1A
1#
0B
0$
0'
03
#133
b11011 &
