Assembly_VerilogAndLogicGates/TTL/sn7404/behaviour.v
//================================================================--
// Design Unit	: sn7404 (behaviour)
//
// File Name	: behaviour.v
//
// Purpose	: model of TTL SN7404 hex inverter IC
//
// Author	: Peter Walsh, Vancouver Island University
//
// Environmant	: Icarus
//-------------------------------------------------------------------
// Revision List	
// Version	Author	Date	Changes
// 1.0		PW	Sept 10 New version
//================================================================--

module sn7404 (P1, P2, P3, P4, P5, P6, P7, P8, P9, P10, P11, P12, P13, P14); 

   output P2, P4, P6, P8, P10, P12;
   input P1, P3, P5, P7, P9, P11, P13, P14;

   reg P2, P4, P6, P8, P10, P12;

   always @(P1, P7, P14) begin

      if ((P14 == 1'b 1) && (P7 == 1'b 0)) begin
         P2 = ~P1;
      end
   end

   always @(P3, P7, P14) begin

      if ((P14 == 1'b 1) && (P7 == 1'b 0)) begin
         P4 = ~P3;
      end
   end

   always @(P5, P7, P14) begin

      if ((P14 == 1'b 1) && (P7 == 1'b 0)) begin
         P6 = ~P5;
      end
   end

   always @(P7, P9, P14) begin

      if ((P14 == 1'b 1) && (P7 == 1'b 0)) begin
         P8 = ~P9;
      end
   end

   always @(P7, P11, P14) begin

      if ((P14 == 1'b 1) && (P7 == 1'b 0)) begin
         P10 = ~P11;
      end
   end

   always @(P7, P13, P14) begin

      if ((P14 == 1'b 1) && (P7 == 1'b 0)) begin
         P12 = ~P13;
      end
   end

endmodule

Assembly_VerilogAndLogicGates/TTL/sn7432/behaviour.v
//================================================================--
// Design Unit	: sn7432 (behaviour) 
//
// File Name	: behaviour.v
//
// Purpose	: model of TTL SN7432 quod or IC
//
// Author	: Peter Walsh, Vancouver Island University
//
// Environmant	: Icarus
//-------------------------------------------------------------------
// Revision List	
// Version	Author	Date	Changes
// 1.0		PW	Sept 10 New version
//================================================================--

module sn7432 (P1, P2, P3, P4, P5, P6, P7, P8, P9, P10, P11, P12, P13, P14); 

   output P3, P6, P8, P11;
   input P1, P2, P4, P5, P7, P9, P10, P12, P13, P14;

   reg P3, P6, P8, P11;

   always @(P1, P2, P7, P14) begin

      if ((P14 == 1'b 1) && (P7 == 1'b 0)) begin
         P3 = P1 | P2;
      end  
   end

   always @(P4, P5, P7, P14) begin

      if ((P14 == 1'b 1) && (P7 == 1'b 0)) begin
         P6 = P4 | P5;
      end  
   end

   always @(P7, P9, P10, P14) begin

      if ((P14 == 1'b 1) && (P7 == 1'b 0)) begin
         P8 = P9 | P10;
      end  
   end

   always @(P7, P12, P13, P14) begin

      if ((P14 == 1'b 1) && (P7 == 1'b 0)) begin
         P11 = P12 | P13;
      end  
   end

endmodule

Assembly_VerilogAndLogicGates/TTL/sn7486/behaviour.v
//================================================================--
// Design Unit	: sn7486 (behaviour) 
//
// File Name	: behaviour.v
//
// Purpose	: model of TTL SN7486 quod xor IC
//
// Author	: Peter Walsh, Vancouver Island University
//
// Environmant	: Icarus
//-------------------------------------------------------------------
// Revision List	
// Version	Author	Date	Changes
// 1.0		PW	Sept 10 New version
//================================================================--

module sn7486 (P1, P2, P3, P4, P5, P6, P7, P8, P9, P10, P11, P12, P13, P14); 

   output P3, P6, P8, P11;
   input P1, P2, P4, P5, P7, P9, P10, P12, P13, P14;

   reg P3, P6, P8, P11;

   always @(P1, P2, P7, P14) begin

      if ((P14 == 1'b 1) && (P7 == 1'b 0)) begin
         P3 = P1 ^ P2;
      end  
   end

   always @(P4, P5, P7, P14) begin

      if ((P14 == 1'b 1) && (P7 == 1'b 0)) begin
         P6 = P4 ^ P5;
      end  
   end

   always @(P7, P9, P10, P14) begin

      if ((P14 == 1'b 1) && (P7 == 1'b 0)) begin
         P8 = P9 ^ P10;
      end  
   end

   always @(P7, P12, P13, P14) begin

      if ((P14 == 1'b 1) && (P7 == 1'b 0)) begin
         P11 = P12 ^ P13;
      end  
   end

endmodule

Assembly_VerilogAndLogicGates/TTL/sn7408/behaviour.v
//================================================================--
// Design Unit	: sn7408 (behaviour) 
//
// File Name	: behaviour.v
//
// Purpose	: model of TTL SN7408 quod and IC
//
// Author	: Peter Walsh, Vancouver Island University
//
// Environmant	: Icarus
//-------------------------------------------------------------------
// Revision List	
// Version	Author	Date	Changes
// 1.0		PW	Sept 10 New version
//================================================================--

module sn7408 (P1, P2, P3, P4, P5, P6, P7, P8, P9, P10, P11, P12, P13, P14); 

   output P3, P6, P8, P11;
   input P1, P2, P4, P5, P7, P9, P10, P12, P13, P14;

   reg P3, P6, P8, P11;

   always @(P1, P2, P7, P14) begin

      if ((P14 == 1'b 1) && (P7 == 1'b 0)) begin
         P3 = P1 & P2;
      end  
   end

   always @(P4, P5, P7, P14) begin

      if ((P14 == 1'b 1) && (P7 == 1'b 0)) begin
         P6 = P4 & P5;
      end  
   end

   always @(P7, P9, P10, P14) begin

      if ((P14 == 1'b 1) && (P7 == 1'b 0)) begin
         P8 = P9 & P10;
      end  
   end

   always @(P7, P12, P13, P14) begin

      if ((P14 == 1'b 1) && (P7 == 1'b 0)) begin
         P11 = P12 & P13;
      end  
   end

endmodule

Assembly_VerilogAndLogicGates/Lab2/ttl.v
//================================================================--
// Design Unit	: lab2 (structural)
//
// File Name	: ttl.v
//
// Purpose	: implement function from lab2
//
// Note		:
//
// Limitations	:
//
// Errors	: none known
//
// Library 	: sn7408, sn7432, sn7404, sn7486
//
// Dependences	: none
//
// Author	: Peter Walsh, Vancouver Island University
//
// Environmant	: Icarus
//-------------------------------------------------------------------
// Revision List	
// Version	Author	Date	Changes
// 1.0		PW	Sept 10 New version
//================================================================--

module lab2 (E, A, B, C, D); 

   output E;
   input A, B, C, D;

   parameter GND=1'b 0, VCC=1'b 1, DC=1'b 0;
   wire I1, I2, I3, I4, A_BAR, B_BAR, C_BAR, D_BAR;

   sn7408 and_gates(A_BAR, C_BAR, I1, B_BAR, C, I3, GND, I4, I2, I1, ,DC ,DC , VCC);
   sn7486 xor_gates(B, D, I2, DC, DC, , GND, ,DC ,DC , ,DC ,DC ,VCC);
   sn7432 or_gates(I3, I4, E, DC ,DC , , GND, ,DC ,DC , ,DC ,DC , VCC);
   sn7404 inv_gates(A, A_BAR, B, B_BAR, C, C_BAR, GND, D_BAR, D, ,DC , ,DC , VCC);

endmodule

Assembly_VerilogAndLogicGates/Lab2/tb.v
//================================================================--
// Design Unit  : cew testbench for lab2
//
// File Name    : tb.cew
//
// Purpose      : design verification
//
// Note         :
//
// Limitations  :
//
// Errors       : none known
//
// Library      : lab2
//
// Dependences  : none
//
// Author       : Peter Walsh, Vancouver Island University
//
// modified by  : Noah Alharbi, -student- Vancouver Island University
//
// System       : icarus (Linux)
//
//------------------------------------------------------------------
// Revision List
// Version      Author  Date    Changes
// 1.0          PW      Sep 10  New version
// 1.1          NA      Oct 9   modified as per lab specification
//================================================================--















module test_bench();

   integer cew_Test_Count=0;
          integer cew_Error_Count=0;

   wire t_E;
   reg t_A, t_B, t_C, t_D;
   integer i;

   // Gold function
    function gold;
       input w,x,y,z;
       gold= (~w & x & ~y & ~z) | (~w & ~x & z) | (y & ~x);
    endfunction


   lab2 cut(t_E, t_A, t_B, t_C, t_D);

   initial begin
      $dumpfile("test_bench.vcd");
      $dumpvars(0,test_bench);

      for (i=0; i<16; i=i+1)
      	  begin
	  cew_Test_Count=cew_Test_Count+1;
          t_A=i[3]; t_B=i[2]; t_C=i[1]; t_D=i[0];#1;
          if ((t_E) !== (gold(t_A, t_B, t_C, t_D))) begin
             cew_Error_Count=cew_Error_Count+1;
             $display("\nTest Case ERROR (Ncase) in script at line number 56");
             $display("Actual Value is ", t_E );
             $display("Expected Value is ", gold(t_A, t_B, t_C, t_D) );
          end

	  end

      $display("\n**********Summary**********\n");
          $display("Total number of test cases = %d \n", cew_Test_Count);
          $display("Total number of test cases in error = %d \n", cew_Error_Count);

      #1 $finish();
   end

endmodule

Assembly_VerilogAndLogicGates/Lab2/ttl.vcd
$date
	Thu Oct 10 01:15:02 2019
$end
$version
	Icarus Verilog
$end
$timescale
	1s
$end
$scope module test_bench $end
$var wire 1 ! t_E $end
$var reg 1 " t_A $end
$var reg 1 # t_B $end
$var reg 1 $ t_C $end
$var reg 1 % t_D $end
$var integer 32 & cew_Error_Count [31:0] $end
$var integer 32 ' cew_Test_Count [31:0] $end
$var integer 32 ( i [31:0] $end
$scope function gold $end
$var reg 1 ) gold $end
$var reg 1 * w $end
$var reg 1 + x $end
$var reg 1 , y $end
$var reg 1 - z $end
$upscope $end
$scope module cut $end
$var wire 1 " A $end
$var wire 1 # B $end
$var wire 1 $ C $end
$var wire 1 % D $end
$var wire 1 . I4 $end
$var wire 1 / I3 $end
$var wire 1 0 I2 $end
$var wire 1 1 I1 $end
$var wire 1 ! E $end
$var wire 1 2 D_BAR $end
$var wire 1 3 C_BAR $end
$var wire 1 4 B_BAR $end
$var wire 1 5 A_BAR $end
$scope module and_gates $end
$var wire 1 6 P12 $end
$var wire 1 7 P13 $end
$var wire 1 8 P14 $end
$var wire 1 $ P5 $end
$var wire 1 9 P7 $end
$var wire 1 0 P9 $end
$var wire 1 4 P4 $end
$var wire 1 3 P2 $end
$var wire 1 1 P10 $end
$var wire 1 5 P1 $end
$var reg 1 : P11 $end
$var reg 1 1 P3 $end
$var reg 1 / P6 $end
$var reg 1 . P8 $end
$upscope $end
$scope module inv_gates $end
$var wire 1 " P1 $end
$var wire 1 ; P11 $end
$var wire 1 < P13 $end
$var wire 1 = P14 $end
$var wire 1 # P3 $end
$var wire 1 $ P5 $end
$var wire 1 > P7 $end
$var wire 1 % P9 $end
$var reg 1 ? P10 $end
$var reg 1 @ P12 $end
$var reg 1 5 P2 $end
$var reg 1 4 P4 $end
$var reg 1 3 P6 $end
$var reg 1 2 P8 $end
$upscope $end
$scope module or_gates $end
$var wire 1 / P1 $end
$var wire 1 A P10 $end
$var wire 1 B P12 $end
$var wire 1 C P13 $end
$var wire 1 D P14 $end
$var wire 1 . P2 $end
$var wire 1 E P4 $end
$var wire 1 F P5 $end
$var wire 1 G P7 $end
$var wire 1 H P9 $end
$var reg 1 I P11 $end
$var reg 1 ! P3 $end
$var reg 1 J P6 $end
$var reg 1 K P8 $end
$upscope $end
$scope module xor_gates $end
$var wire 1 # P1 $end
$var wire 1 L P10 $end
$var wire 1 M P12 $end
$var wire 1 N P13 $end
$var wire 1 O P14 $end
$var wire 1 % P2 $end
$var wire 1 P P4 $end
$var wire 1 Q P5 $end
$var wire 1 R P7 $end
$var wire 1 S P9 $end
$var reg 1 T P11 $end
$var reg 1 0 P3 $end
$var reg 1 U P6 $end
$var reg 1 V P8 $end
$upscope $end
$upscope $end
$upscope $end
$enddefinitions $end
#0
$dumpvars
0V
0U
0T
0S
0R
0Q
0P
1O
0N
0M
0L
0K
0J
0I
0H
0G
0F
0E
1D
0C
0B
0A
1@
1?
0>
1=
0<
0;
0:
09
18
07
06
15
14
13
12
11
00
0/
0.
x-
x,
x+
x*
x)
b0 (
b1 '
b0 &
0%
0$
0#
0"
0!
$end
#1
1!
1.
02
10
1%
b10 '
b1 (
0)
0*
0+
0,
0-
#2
0.
01
12
00
1/
03
0%
1$
b11 '
b10 (
1)
1-
#3
02
10
1%
b100 '
b11 (
1,
0-
#4
1.
1!
11
12
0/
13
04
0%
0$
1#
b101 '
b100 (
1-
#5
0!
0.
02
00
1%
b110 '
b101 (
1+
0,
0-
#6
01
12
10
03
0%
1$
b111 '
b110 (
0)
1-
#7
02
00
1%
b1000 '
b111 (
1,
0-
#8
12
13
14
05
0%
0$
0#
1"
b1001 '
b1000 (
1-
#9
02
10
1%
b1010 '
b1001 (
1*
0+
0,
0-
#10
1!
12
00
1/
03
0%
1$
b1011 '
b1010 (
1-
#11
02
10
1%
b1100 '
b1011 (
1)
1,
0-
#12
0!
12
0/
13
04
0%
0$
1#
b1101 '
b1100 (
1-
#13
02
00
1%
b1110 '
b1101 (
0)
1+
0,
0-
#14
12
10
03
0%
1$
b1111 '
b1110 (
1-
#15
02
00
1%
b10000 '
b1111 (
1,
0-
#16
b10000 (
1-
