Assembly_VerilogAndLogicGates/TTL/sn74175/behaviour.v
//================================================================--
// Design Unit	: sn74175 (behaviour) 
//
// File Name	: behaviour.v
//
// Purpose	: model of TTL SN74175 quod D FF IC
//
// Author	: Peter Walsh, Vancouver Island University
//
// Environmant	: Icarus
//-------------------------------------------------------------------
// Revision List	
// Version	Author	Date	Changes
// 1.0		PW	Sept 10 New version
//================================================================--

module sn74175 (P1, P2, P3, P4, P5, P6, P7, P8, P9, P10, P11, P12, P13, P14, P15, P16); 

   output reg P2, P3, P6, P7, P10, P11, P14, P15;
   input P1, P4, P5, P8, P9, P12, P13, P16;

   always @ (posedge P9) begin
      if ((P16 == 1'b 1) && (P8 == 1'b 0)) begin
         // Q0 and Q0_BAR
         P2 <= P4;
         P3 <= ~P4;
         // Q1 and Q1_BAR
         P7 <= P5;
         P6 <= ~P5;
         // Q2 and Q2_BAR
         P10 <= P12;
         P11 <= ~P12;
         // Q3 and Q3_BAR
         P15 <= P13;
         P14 <= ~P13;
      end
   end

   always @ (P1) begin
      if ((P16 == 1'b 1) && (P8 == 1'b 0)) begin
         if (P1 == 0) begin
            // Q0 and Q0_BAR
            P2 <= 1'b0;
            P3 <= 1'b1;
            // Q1 and Q1_BAR
            P7 <= 1'b0;
            P6 <= 1'b1;
            // Q2 and Q2_BAR
            P10 <= 1'b0;
            P11 <= 1'b1;
            // Q3 and Q3_BAR
            P15 <= 1'b0;
            P14 <= 1'b1;
         end
      end
   end

endmodule

Assembly_VerilogAndLogicGates/TTL/sn74175/tb.v
//================================================================--
// Design Unit  : cew testbench for sn74175
//
// File Name    : tb.cew
//
// Purpose      : design verification
//
// Author       : Peter Walsh, Vancouver Island University
//
// System       : icarus (Linux)
//
//------------------------------------------------------------------
// Revision List
// Version      Author  Date    Changes
// 1.0          PW      Sep 10  New version
//================================================================--











module test_bench();

   integer cew_Test_Count=0;
          integer cew_Error_Count=0;

   wire t_P2, t_P3, t_P6, t_P7, t_P10, t_P11, t_P14, t_P15;
   reg t_P1, t_P4, t_P5, t_P8, t_P9, t_P12, t_P13, t_P16;

   sn74175 cut(t_P1, t_P2, t_P3, t_P4, t_P5, t_P6, t_P7, t_P8, t_P9, t_P10, t_P11, t_P12, t_P13, t_P14, t_P15, t_P16);

   task clockTick; // nasty syntax but task body can only be one (compound) statement
      begin
         t_P9=0; #3;
         t_P9=1; #6;
         t_P9=0; #3;
      end
   endtask

   // Test Master Reset - asynchronous active low

   task testMasterReset; begin
      cew_Test_Count=cew_Test_Count+1;
          t_P1<=0;#1;t_P1<=1;#1;
          if ((t_P2) !== (0)) begin
             cew_Error_Count=cew_Error_Count+1;
             $display("\nTest Case ERROR (Ncase) in script at line number 39");
             $display("Actual Value is ", t_P2 );
             $display("Expected Value is ", 0 );
          end

      cew_Test_Count=cew_Test_Count+1;
          
          if ((t_P3) !== (1)) begin
             cew_Error_Count=cew_Error_Count+1;
             $display("\nTest Case ERROR (Ncase) in script at line number 40");
             $display("Actual Value is ", t_P3 );
             $display("Expected Value is ", 1 );
          end


      cew_Test_Count=cew_Test_Count+1;
          
          if ((t_P7) !== (0)) begin
             cew_Error_Count=cew_Error_Count+1;
             $display("\nTest Case ERROR (Ncase) in script at line number 42");
             $display("Actual Value is ", t_P7 );
             $display("Expected Value is ", 0 );
          end

      cew_Test_Count=cew_Test_Count+1;
          
          if ((t_P6) !== (1)) begin
             cew_Error_Count=cew_Error_Count+1;
             $display("\nTest Case ERROR (Ncase) in script at line number 43");
             $display("Actual Value is ", t_P6 );
             $display("Expected Value is ", 1 );
          end


      cew_Test_Count=cew_Test_Count+1;
          
          if ((t_P10) !== (0)) begin
             cew_Error_Count=cew_Error_Count+1;
             $display("\nTest Case ERROR (Ncase) in script at line number 45");
             $display("Actual Value is ", t_P10 );
             $display("Expected Value is ", 0 );
          end

      cew_Test_Count=cew_Test_Count+1;
          
          if ((t_P11) !== (1)) begin
             cew_Error_Count=cew_Error_Count+1;
             $display("\nTest Case ERROR (Ncase) in script at line number 46");
             $display("Actual Value is ", t_P11 );
             $display("Expected Value is ", 1 );
          end


      cew_Test_Count=cew_Test_Count+1;
          
          if ((t_P15) !== (0)) begin
             cew_Error_Count=cew_Error_Count+1;
             $display("\nTest Case ERROR (Ncase) in script at line number 48");
             $display("Actual Value is ", t_P15 );
             $display("Expected Value is ", 0 );
          end

      cew_Test_Count=cew_Test_Count+1;
          
          if ((t_P14) !== (1)) begin
             cew_Error_Count=cew_Error_Count+1;
             $display("\nTest Case ERROR (Ncase) in script at line number 49");
             $display("Actual Value is ", t_P14 );
             $display("Expected Value is ", 1 );
          end

   end
   endtask

   initial begin
      $dumpfile("test_bench.vcd");
      $dumpvars(0,test_bench);

      t_P16=1; t_P8=0;

      // Async Operation

      testMasterReset();

      // Normal Operation

      cew_Test_Count=cew_Test_Count+1;
          t_P4=1;clockTick();
          if ((t_P2) !== (1)) begin
             cew_Error_Count=cew_Error_Count+1;
             $display("\nTest Case ERROR (Ncase) in script at line number 65");
             $display("Actual Value is ", t_P2 );
             $display("Expected Value is ", 1 );
          end

      cew_Test_Count=cew_Test_Count+1;
          
          if ((t_P3) !== (0)) begin
             cew_Error_Count=cew_Error_Count+1;
             $display("\nTest Case ERROR (Ncase) in script at line number 66");
             $display("Actual Value is ", t_P3 );
             $display("Expected Value is ", 0 );
          end


      cew_Test_Count=cew_Test_Count+1;
          t_P5=1;clockTick();
          if ((t_P7) !== (1)) begin
             cew_Error_Count=cew_Error_Count+1;
             $display("\nTest Case ERROR (Ncase) in script at line number 68");
             $display("Actual Value is ", t_P7 );
             $display("Expected Value is ", 1 );
          end

      cew_Test_Count=cew_Test_Count+1;
          
          if ((t_P6) !== (0)) begin
             cew_Error_Count=cew_Error_Count+1;
             $display("\nTest Case ERROR (Ncase) in script at line number 69");
             $display("Actual Value is ", t_P6 );
             $display("Expected Value is ", 0 );
          end


      cew_Test_Count=cew_Test_Count+1;
          t_P12=1;clockTick();
          if ((t_P10) !== (1)) begin
             cew_Error_Count=cew_Error_Count+1;
             $display("\nTest Case ERROR (Ncase) in script at line number 71");
             $display("Actual Value is ", t_P10 );
             $display("Expected Value is ", 1 );
          end

      cew_Test_Count=cew_Test_Count+1;
          
          if ((t_P11) !== (0)) begin
             cew_Error_Count=cew_Error_Count+1;
             $display("\nTest Case ERROR (Ncase) in script at line number 72");
             $display("Actual Value is ", t_P11 );
             $display("Expected Value is ", 0 );
          end


      cew_Test_Count=cew_Test_Count+1;
          t_P13=1;clockTick();
          if ((t_P15) !== (1)) begin
             cew_Error_Count=cew_Error_Count+1;
             $display("\nTest Case ERROR (Ncase) in script at line number 74");
             $display("Actual Value is ", t_P15 );
             $display("Expected Value is ", 1 );
          end

      cew_Test_Count=cew_Test_Count+1;
          
          if ((t_P14) !== (0)) begin
             cew_Error_Count=cew_Error_Count+1;
             $display("\nTest Case ERROR (Ncase) in script at line number 75");
             $display("Actual Value is ", t_P14 );
             $display("Expected Value is ", 0 );
          end



      cew_Test_Count=cew_Test_Count+1;
          t_P4=0;clockTick();
          if ((t_P2) !== (0)) begin
             cew_Error_Count=cew_Error_Count+1;
             $display("\nTest Case ERROR (Ncase) in script at line number 78");
             $display("Actual Value is ", t_P2 );
             $display("Expected Value is ", 0 );
          end

      cew_Test_Count=cew_Test_Count+1;
          
          if ((t_P3) !== (1)) begin
             cew_Error_Count=cew_Error_Count+1;
             $display("\nTest Case ERROR (Ncase) in script at line number 79");
             $display("Actual Value is ", t_P3 );
             $display("Expected Value is ", 1 );
          end


      cew_Test_Count=cew_Test_Count+1;
          t_P5=0;clockTick();
          if ((t_P7) !== (0)) begin
             cew_Error_Count=cew_Error_Count+1;
             $display("\nTest Case ERROR (Ncase) in script at line number 81");
             $display("Actual Value is ", t_P7 );
             $display("Expected Value is ", 0 );
          end

      cew_Test_Count=cew_Test_Count+1;
          
          if ((t_P6) !== (1)) begin
             cew_Error_Count=cew_Error_Count+1;
             $display("\nTest Case ERROR (Ncase) in script at line number 82");
             $display("Actual Value is ", t_P6 );
             $display("Expected Value is ", 1 );
          end


      cew_Test_Count=cew_Test_Count+1;
          t_P12=0;clockTick();
          if ((t_P10) !== (0)) begin
             cew_Error_Count=cew_Error_Count+1;
             $display("\nTest Case ERROR (Ncase) in script at line number 84");
             $display("Actual Value is ", t_P10 );
             $display("Expected Value is ", 0 );
          end

      cew_Test_Count=cew_Test_Count+1;
          
          if ((t_P11) !== (1)) begin
             cew_Error_Count=cew_Error_Count+1;
             $display("\nTest Case ERROR (Ncase) in script at line number 85");
             $display("Actual Value is ", t_P11 );
             $display("Expected Value is ", 1 );
          end


      cew_Test_Count=cew_Test_Count+1;
          t_P13=0;clockTick();
          if ((t_P15) !== (0)) begin
             cew_Error_Count=cew_Error_Count+1;
             $display("\nTest Case ERROR (Ncase) in script at line number 87");
             $display("Actual Value is ", t_P15 );
             $display("Expected Value is ", 0 );
          end

      cew_Test_Count=cew_Test_Count+1;
          
          if ((t_P14) !== (1)) begin
             cew_Error_Count=cew_Error_Count+1;
             $display("\nTest Case ERROR (Ncase) in script at line number 88");
             $display("Actual Value is ", t_P14 );
             $display("Expected Value is ", 1 );
          end



      $display("\n**********Summary**********\n");
          $display("Total number of test cases = %d \n", cew_Test_Count);
          $display("Total number of test cases in error = %d \n", cew_Error_Count);

      #1 $finish();
   end

endmodule

Assembly_VerilogAndLogicGates/TTL/sn74175/test_bench.vcd
$date
	Thu Nov 21 15:50:35 2013
$end
$version
	Icarus Verilog
$end
$timescale
	1s
$end
$scope module test_bench $end
$var wire 1 ! t_P10 $end
$var wire 1 " t_P11 $end
$var wire 1 # t_P14 $end
$var wire 1 $ t_P15 $end
$var wire 1 % t_P2 $end
$var wire 1 & t_P3 $end
$var wire 1 ' t_P6 $end
$var wire 1 ( t_P7 $end
$var integer 32 ) cew_Error_Count [31:0] $end
$var integer 32 * cew_Test_Count [31:0] $end
$var reg 1 + t_P1 $end
$var reg 1 , t_P12 $end
$var reg 1 - t_P13 $end
$var reg 1 . t_P16 $end
$var reg 1 / t_P4 $end
$var reg 1 0 t_P5 $end
$var reg 1 1 t_P8 $end
$var reg 1 2 t_P9 $end
$scope module cut $end
$var wire 1 3 P1 $end
$var wire 1 4 P12 $end
$var wire 1 5 P13 $end
$var wire 1 6 P16 $end
$var wire 1 7 P4 $end
$var wire 1 8 P5 $end
$var wire 1 9 P8 $end
$var wire 1 : P9 $end
$var reg 1 ; P10 $end
$var reg 1 < P11 $end
$var reg 1 = P14 $end
$var reg 1 > P15 $end
$var reg 1 ? P2 $end
$var reg 1 @ P3 $end
$var reg 1 A P6 $end
$var reg 1 B P7 $end
$upscope $end
$scope task clockTick $end
$upscope $end
$scope task testMasterReset $end
$upscope $end
$upscope $end
$enddefinitions $end
#0
$dumpvars
0B
1A
1@
0?
0>
1=
1<
0;
x:
09
x8
x7
16
x5
x4
03
x2
01
x0
x/
1.
x-
x,
0+
b1 *
b0 )
0(
1'
1&
0%
0$
1#
1"
0!
$end
#1
1+
13
#2
02
0:
1/
17
b1001 *
#5
x=
x#
x>
x$
x<
x"
x;
x!
xA
x'
xB
x(
0@
0&
1?
1%
12
1:
#11
02
0:
#14
10
18
b1011 *
#17
0A
0'
1B
1(
12
1:
#23
02
0:
#26
1,
14
b1101 *
#29
0<
0"
1;
1!
12
1:
#35
02
0:
#38
1-
15
b1111 *
#41
0=
0#
1>
1$
12
1:
#47
02
0:
#50
0/
07
b10001 *
#53
1@
1&
0?
0%
12
1:
#59
02
0:
#62
00
08
b10011 *
#65
1A
1'
0B
0(
12
1:
#71
02
0:
#74
0,
04
b10101 *
#77
1<
1"
0;
0!
12
1:
#83
02
0:
#86
0-
05
b10111 *
#89
1=
1#
0>
0$
12
1:
#95
02
0:
#98
b11000 *
